{"lastUsed":1702480991747,"path":"C:\/Users\/ymnN\/Desktop\/learn-spring","projectCount":1,"recentFiles":[{"path":"\/01-rest-api-starting-code","parentWorkspace":"C:\/Users\/ymnN\/Desktop\/learn-spring","name":"pom.xml","lastModified":1702374258588,"locationURI":"file:\/C:\/Users\/ymnN\/Desktop\/learn-spring\/01-rest-api-starting-code\/pom.xml"},{"path":"\/01-rest-api-starting-code\/src\/main\/java\/com\/in28minutes\/rest\/webservices\/restfulwebservices","parentWorkspace":"C:\/Users\/ymnN\/Desktop\/learn-spring","name":"RestfulWebServicesApplication.java","lastModified":1702477840315,"locationURI":"file:\/C:\/Users\/ymnN\/Desktop\/learn-spring\/01-rest-api-starting-code\/src\/main\/java\/com\/in28minutes\/rest\/webservices\/restfulwebservices\/RestfulWebServicesApplication.java"},{"path":"\/01-rest-api-starting-code\/src\/main\/java\/com\/in28minutes\/rest\/webservices\/restfulwebservices\/todo","parentWorkspace":"C:\/Users\/ymnN\/Desktop\/learn-spring","name":"TodoResource.java","lastModified":1702478826443,"locationURI":"file:\/C:\/Users\/ymnN\/Desktop\/learn-spring\/01-rest-api-starting-code\/src\/main\/java\/com\/in28minutes\/rest\/webservices\/restfulwebservices\/todo\/TodoResource.java"},{"path":"\/01-rest-api-starting-code\/src\/main\/resources","parentWorkspace":"C:\/Users\/ymnN\/Desktop\/learn-spring","name":"application.properties","lastModified":1702374069075,"locationURI":"file:\/C:\/Users\/ymnN\/Desktop\/learn-spring\/01-rest-api-starting-code\/src\/main\/resources\/application.properties"}]}